facemosaic/__init__.py
facemosaic/facemosaic.py
facemosaic/model/Caffe/deploy.prototxt
facemosaic/model/Caffe/res10_300x300_ssd_iter_140000_fp16.caffemodel
facemosaic-1.1.0.dist-info/METADATA
facemosaic-1.1.0.dist-info/WHEEL
facemosaic-1.1.0.dist-info/top_level.txt
facemosaic-1.1.0.dist-info/RECORD
