Metadata-Version: 2.1
Name: facemosaic
Version: 1.1.0
Summary: 自动识别图片中人脸并加上马赛克
Home-page: https://help.hlstudio.ren/020400.html
Author: 刘子豪
Author-email: 2740994541@qq.com
License: UNKNOWN
Platform: UNKNOWN
Requires-Python: >=3
Requires-Dist: opencv-python
